lqrax/__init__.py
lqrax/ilqr.py
lqrax/lqr.py
lqrax-0.0.6.dist-info/licenses/LICENSE
lqrax-0.0.6.dist-info/METADATA
lqrax-0.0.6.dist-info/WHEEL
lqrax-0.0.6.dist-info/top_level.txt
lqrax-0.0.6.dist-info/RECORD
