Metadata-Version: 2.4
Name: lqrax
Version: 0.0.6
Summary: JAX-enabled continuous-time Riccati equation solver
Home-page: https://github.com/maxmsun/lqrax
Author: Max Muchen Sun
Author-email: msun@u.northwestern.edu
License: GPLv3
Classifier: Programming Language :: Python :: 3
Classifier: License :: OSI Approved :: GNU General Public License v3 (GPLv3)
Classifier: Operating System :: OS Independent
Requires-Python: >=3.8
License-File: LICENSE
Dynamic: author
Dynamic: author-email
Dynamic: classifier
Dynamic: description
Dynamic: description-content-type
Dynamic: home-page
Dynamic: license
Dynamic: license-file
Dynamic: requires-python
Dynamic: summary
